partial_rankings/__init__.py
partial_rankings/dataset.py
partial_rankings/decos.py
partial_rankings/model.py
partial_rankings/preprocessing.py
partial_rankings/utils.py
partial_rankings-1.0.0.dist-info/LICENSE
partial_rankings-1.0.0.dist-info/WHEEL
partial_rankings-1.0.0.dist-info/METADATA
partial_rankings-1.0.0.dist-info/RECORD
