Metadata-Version: 2.3
Name: partial_rankings
Version: 1.0.0
Summary: Infer partial rankings from a series of pairwise comparisons.
Author: Sebastian Morel-Balbi
Requires-Python: ~=3.11.9
Classifier: Programming Language :: Python :: 3
Classifier: License :: OSI Approved :: GNU General Public License v3 (GPLv3)
